autohaus_updater/__init__.py
autohaus_updater/_version.py
autohaus_updater/main.py
autohaus_updater-0.0.6.dist-info/METADATA
autohaus_updater-0.0.6.dist-info/WHEEL
autohaus_updater-0.0.6.dist-info/RECORD
